dq_tool/__init__.py
dq_tool/__version__.py
dq_tool/custom_expectations.py
dq_tool/dq_tool.py
dq_tool/expectation_attributes/__init__.py
dq_tool/expectation_attributes/expectation.py
dq_tool/expectation_attributes/expectation_suite.py
dq_tool/expectation_attributes/read_only_attributes.py
dq_tool/expectation_store.py
dq_tool/expectation_suite_store.py
dq_tool/expressions.py
dq_tool/great_expectations_config.py
dq_tool/hive_metastore.py
dq_tool/misc/__init__.py
dq_tool/misc/databricks.py
dq_tool/misc/printing.py
dq_tool/misc/user_identity_provider.py
dq_tool/misc/yaml.py
dq_tool/playground.py
dq_tool/validation_result.py
dq_tool-0.0.4.dist-info/WHEEL
dq_tool-0.0.4.dist-info/METADATA
dq_tool-0.0.4.dist-info/RECORD
