Metadata-Version: 2.1
Name: dq-tool
Version: 0.0.4
Summary: 
Home-page: https://github.com/DataSentics/dq_tool
Author: DataSentics
Author-email: info@datasentics.com
Requires-Python: >=3.7,<4.0
Classifier: Operating System :: OS Independent
Classifier: Programming Language :: Python :: 3
Classifier: Programming Language :: Python :: 3.7
Classifier: Programming Language :: Python :: 3.8
Requires-Dist: great-expectations (>=0.13.0,<0.14.0)
Requires-Dist: sqlalchemy (>=1.3.16)
Project-URL: Repository, https://github.com/DataSentics/dq_tool
